pyvfc.cpython-35m-x86_64-linux-gnu.so
.libspyvfc/libopencv_highgui-6fc58933.so.3.4.9
.libspyvfc/libopencv_core-15ccb8e7.so.3.4.9
.libspyvfc/libopencv_imgcodecs-356773c1.so.3.4.9
.libspyvfc/libopencv_videoio-36f9035f.so.3.4.9
.libspyvfc/libopencv_imgproc-dc3af61f.so.3.4.9
pyvfc-0.0.2.dist-info/METADATA
pyvfc-0.0.2.dist-info/RECORD
pyvfc-0.0.2.dist-info/WHEEL
pyvfc-0.0.2.dist-info/top_level.txt
